{
  "nodes": [
    {
      "body": "{!header} Welcome to the end of February everyone! You made it! Tomorrow is Leap Day! Or, more importantly \"Call in 'sick' to work because I'm going to be playing FF7:Rebirth\" day!"
    },
    {
      "body": "{🎮 releases} [qomp2](https://urals.co/atari/qomp2) by [Graphite Lab](https://graphitelab.com/) & Atari is out now!"
    },
    {
      "body": "{🔜 coming soon} [Serafina's Saga: Awakened](https://store.epicgames.com/en-US/p/serafinas-saga-awakened-921f2a) by [Woodsy Studio](https://woodsy-studio.com/) is an otome-styled narrative adventure scheduled for release on March 19th! Wishlist it today on the Epic Games Store!"
    },
    {
      "body": "{📅 events} The next [Share and Play](https://www.meetup.com/st-louis-game-developers/events/299057965/) event will be on March 24th at Webster University! Bring your game projects to show off and get feedback!"
    }
  ]
}
